crawlerUtils/__init__.py
crawlerUtils/utils.py
crawlerUtils/base64decodeTools/__init__.py
crawlerUtils/base64decodeTools/decodeTool.py
crawlerUtils/captcha/__init__.py
crawlerUtils/captcha/captchaRecognizeMain.py
crawlerUtils/captcha/captchaTestSetCreate.py
crawlerUtils/captcha/recognizeCaptchaMain.py
crawlerUtils/captcha/captcha_set/.DS_Store
crawlerUtils/captcha/captcha_set/0/.DS_Store
crawlerUtils/captcha/captcha_set/1/.DS_Store
crawlerUtils/captcha/captcha_set/2/23d8861da508ba30d98dc5cc2ece37a2.jpeg
crawlerUtils/captcha/captcha_set/2/90493a86fccf7ac0c19cf4d7f977a6f4.jpeg
crawlerUtils/captcha/captcha_set/2/c3e99e8094bced29d0a6440feb77795b.jpeg
crawlerUtils/captcha/captcha_set/2/captcha__11___1.jpeg
crawlerUtils/captcha/captcha_set/2/captcha__12___4.jpeg
crawlerUtils/captcha/captcha_set/2/captcha__1___2.jpeg
crawlerUtils/captcha/captcha_set/2/captcha__24___2.jpeg
crawlerUtils/captcha/captcha_set/2/captcha__41___4.jpeg
crawlerUtils/captcha/captcha_set/2/captcha__42___3.jpeg
crawlerUtils/captcha/captcha_set/2/captcha__43___2.jpeg
crawlerUtils/captcha/captcha_set/2/captcha__57___1.jpeg
crawlerUtils/captcha/captcha_set/2/captcha__59___3.jpeg
crawlerUtils/captcha/captcha_set/2/captcha__70___1.jpeg
crawlerUtils/captcha/captcha_set/2/captcha__70___3.jpeg
crawlerUtils/captcha/captcha_set/2/captcha__72___1.jpeg
crawlerUtils/captcha/captcha_set/2/captcha__78___1.jpeg
crawlerUtils/captcha/captcha_set/2/captcha__78___3.jpeg
crawlerUtils/captcha/captcha_set/2/captcha_binary___1.jpeg
crawlerUtils/captcha/captcha_set/2/captcha_binary___4.jpeg
crawlerUtils/captcha/captcha_set/3/14fc71f458355b93107368dec714816b.jpeg
crawlerUtils/captcha/captcha_set/3/ad6a0d6ddb6e4c90067e0d63bb903ed0.jpeg
crawlerUtils/captcha/captcha_set/3/captcha__15___2.jpeg
crawlerUtils/captcha/captcha_set/3/captcha__21___2.jpeg
crawlerUtils/captcha/captcha_set/3/captcha__22___3.jpeg
crawlerUtils/captcha/captcha_set/3/captcha__25___2.jpeg
crawlerUtils/captcha/captcha_set/3/captcha__26___3.jpeg
crawlerUtils-1.8.1.post4.dist-info/LICENSE
crawlerUtils-1.8.1.post4.dist-info/METADATA
crawlerUtils-1.8.1.post4.dist-info/WHEEL
crawlerUtils-1.8.1.post4.dist-info/top_level.txt
crawlerUtils-1.8.1.post4.dist-info/RECORD
