Metadata-Version: 2.1
Name: crawlerUtils
Version: 1.8.1.post4
Summary: Crawler Utils examples
Home-page: https://github.com/Tyrone-Zhao/crawlerUtils
Author: Tyrone Zhao
Author-email: tyrone-zhao@qq.com
License: UNKNOWN
Project-URL: Blog, https://blog.csdn.net/weixin_41845533
Keywords: crawler html selenium-python python3 requests beautifulsoup4 urllib mail schedule captcha excel scraping log requests-html csv gevent spiders geohash base64
Platform: UNKNOWN
Classifier: Development Status :: 3 - Alpha
Classifier: Intended Audience :: Developers
Classifier: Topic :: Software Development :: Code Generators
Classifier: License :: OSI Approved :: MIT License
Classifier: Programming Language :: Python :: 3.6
Classifier: Programming Language :: Python
Requires-Python: >=3.6.0
Requires-Dist: bs4 (>=0.0.1)
Requires-Dist: selenium (>=3.141.0)
Requires-Dist: schedule (>=0.6.0)
Requires-Dist: xlrd (>=1.2.0)
Requires-Dist: xlwt (>=1.3.0)
Requires-Dist: gevent (>=1.4.0)
Requires-Dist: requests-html (>=0.10.0)
Requires-Dist: Pillow (>=5.3.0)
Requires-Dist: pymongo (>=3.7.2)
